{"assets/images/G.E.png":["assets/images/G.E.png"],"assets/images/dribbble.png":["assets/images/dribbble.png"],"assets/images/github.png":["assets/images/github.png"],"assets/images/heromobile.png":["assets/images/heromobile.png"],"assets/images/heroweb.png":["assets/images/heroweb.png"],"assets/images/instagram.png":["assets/images/instagram.png"],"assets/images/technologies.png":["assets/images/technologies.png"],"assets/images/x.png":["assets/images/x.png"],"packages/cupertino_icons/assets/CupertinoIcons.ttf":["packages/cupertino_icons/assets/CupertinoIcons.ttf"],"packages/iconsax/lib/assets/fonts/iconsax.ttf":["packages/iconsax/lib/assets/fonts/iconsax.ttf"]}